uberduct/__init__.py
uberduct/uberduct.py
uberduct/dict/cmudict.dict
uberduct/dict/cmudict.phones
uberduct/dict/cmudict.symbols
uberduct/dict/cmudict.vp
uberduct-0.0.5.data/data/dict/cmudict.dict
uberduct-0.0.5.dist-info/LICENSE
uberduct-0.0.5.dist-info/METADATA
uberduct-0.0.5.dist-info/WHEEL
uberduct-0.0.5.dist-info/top_level.txt
uberduct-0.0.5.dist-info/RECORD
