Metadata-Version: 2.1
Name: uberduct
Version: 0.0.5
Summary: Augmenting the CMU dictionary
Home-page: https://github.com/uberduck-ai/uberduct
Author: Zach Wener
Author-email: info@uberduck.ai
Project-URL: Bug Tracker, https://github.com/pypa/sampleproject/issues
Classifier: Programming Language :: Python :: 3
Classifier: License :: OSI Approved :: MIT License
Classifier: Operating System :: OS Independent
Requires-Python: >=3.6
License-File: LICENSE
